pybluedot/__init__.py
pybluedot/bluedot.py
pybluedot/config.py
pybluedot-0.2.1.dist-info/DESCRIPTION.rst
pybluedot-0.2.1.dist-info/METADATA
pybluedot-0.2.1.dist-info/RECORD
pybluedot-0.2.1.dist-info/WHEEL
pybluedot-0.2.1.dist-info/entry_points.txt
pybluedot-0.2.1.dist-info/metadata.json
pybluedot-0.2.1.dist-info/top_level.txt
