Metadata-Version: 2.0
Name: pybluedot
Version: 0.2.1
Summary: BluedotSMS python wrapper
Home-page: http://github.com/ignertic/pybluedot
Author: Gishobert Gwenzi
Author-email: ilovebugsincode@gmail.com
License: MIT
Platform: UNKNOWN
Classifier: Programming Language :: Python :: 3
Classifier: Operating System :: OS Independent
Requires-Dist: loguru
Requires-Dist: requests
